{
    "overrides":[
        {"predicate":{"custom_model_data":1},"model":"modelengine:volcano_lizard_chibi/torso"},
        {"predicate":{"custom_model_data":2},"model":"modelengine:volcano_lizard_chibi/leg_front_left"},
        {"predicate":{"custom_model_data":3},"model":"modelengine:volcano_lizard_chibi/horn_middle5"},
        {"predicate":{"custom_model_data":4},"model":"modelengine:volcano_lizard_chibi/head"},
        {"predicate":{"custom_model_data":5},"model":"modelengine:volcano_lizard_chibi/leg_front_right"},
        {"predicate":{"custom_model_data":6},"model":"modelengine:volcano_lizard_chibi/tail"},
        {"predicate":{"custom_model_data":7},"model":"modelengine:volcano_lizard_chibi/horn_middle4"},
        {"predicate":{"custom_model_data":8},"model":"modelengine:volcano_lizard_chibi/leg_back_right"},
        {"predicate":{"custom_model_data":9},"model":"modelengine:volcano_lizard_chibi/leg_back_left"},
        {"predicate":{"custom_model_data":10},"model":"modelengine:volcano_lizard_chibi/tibia_front_right"},
        {"predicate":{"custom_model_data":11},"model":"modelengine:volcano_lizard_chibi/tibia_back_left"},
        {"predicate":{"custom_model_data":12},"model":"modelengine:volcano_lizard_chibi/tibia_front_left"},
        {"predicate":{"custom_model_data":13},"model":"modelengine:volcano_lizard_chibi/tibia_back_right"},
        {"predicate":{"custom_model_data":14},"model":"modelengine:volcano_lizard_chibi/tail_end"},
        {"predicate":{"custom_model_data":15},"model":"modelengine:volcano_lizard_chibi/jaw"},
        {"predicate":{"custom_model_data":16},"model":"modelengine:volcano_lizard_chibi/horn_left"},
        {"predicate":{"custom_model_data":17},"model":"modelengine:volcano_lizard_chibi/horn_right"},
        {"predicate":{"custom_model_data":18},"model":"modelengine:volcano_lizard_chibi/horn_middle"},
        {"predicate":{"custom_model_data":19},"model":"modelengine:volcano_lizard_ascendant/leg_front_right"},
        {"predicate":{"custom_model_data":20},"model":"modelengine:volcano_lizard_ascendant/torso"},
        {"predicate":{"custom_model_data":21},"model":"modelengine:volcano_lizard_ascendant/leg_back_left"},
        {"predicate":{"custom_model_data":22},"model":"modelengine:volcano_lizard_ascendant/leg_front_left"},
        {"predicate":{"custom_model_data":23},"model":"modelengine:volcano_lizard_ascendant/leg_back_right"},
        {"predicate":{"custom_model_data":24},"model":"modelengine:volcano_lizard_ascendant/tibia_front_right"},
        {"predicate":{"custom_model_data":25},"model":"modelengine:volcano_lizard_ascendant/horn_middle3"},
        {"predicate":{"custom_model_data":26},"model":"modelengine:volcano_lizard_ascendant/torso_low"},
        {"predicate":{"custom_model_data":27},"model":"modelengine:volcano_lizard_ascendant/horn_middle5"},
        {"predicate":{"custom_model_data":28},"model":"modelengine:volcano_lizard_ascendant/neck"},
        {"predicate":{"custom_model_data":29},"model":"modelengine:volcano_lizard_ascendant/tibia_back_left"},
        {"predicate":{"custom_model_data":30},"model":"modelengine:volcano_lizard_ascendant/tibia_front_left"},
        {"predicate":{"custom_model_data":31},"model":"modelengine:volcano_lizard_ascendant/tibia_back_right"},
        {"predicate":{"custom_model_data":32},"model":"modelengine:volcano_lizard_ascendant/horn_middle6"},
        {"predicate":{"custom_model_data":33},"model":"modelengine:volcano_lizard_ascendant/horn_middle2"},
        {"predicate":{"custom_model_data":34},"model":"modelengine:volcano_lizard_ascendant/tail"},
        {"predicate":{"custom_model_data":35},"model":"modelengine:volcano_lizard_ascendant/horn_middle4"},
        {"predicate":{"custom_model_data":36},"model":"modelengine:volcano_lizard_ascendant/head"},
        {"predicate":{"custom_model_data":37},"model":"modelengine:volcano_lizard_ascendant/tail_end"},
        {"predicate":{"custom_model_data":38},"model":"modelengine:volcano_lizard_ascendant/jaw"},
        {"predicate":{"custom_model_data":39},"model":"modelengine:volcano_lizard_ascendant/horn_left"},
        {"predicate":{"custom_model_data":40},"model":"modelengine:volcano_lizard_ascendant/horn_right"},
        {"predicate":{"custom_model_data":41},"model":"modelengine:volcano_lizard_ascendant/horn_middle"}
    ],
    "parent":"minecraft:item/generated",
    "textures":{"layer0":"minecraft:item/leather_horse_armor"}
}